{"ArtsF":["null"], "ArtsW":["null"], "ArtsFY":["null"], "MedicineF":["null"], "MedicineW":["null"], "MedicineFY":["null"], "ArchitectureF":["null"], "ArchitectureW":["null"], "ArchitectureFY":["null"], "BusinessF":["null"], "BusinessW":["null"], "BusinessFY":["null"], "KinesiologyF":["null"], "KinesiologyW":["null"], "KinesiologyFY":["null"], "LawF":["null"], "LawW":["null"], "LawFY":["null"], "NursingF":["null"], "NursingW":["null"], "NursingFY":["null"], "EngineeringF":["null"], "EngineeringW":["null"], "EngineeringFY":["null"], "Social WorkF":["null"], "Social WorkW":["null"], "Social WorkFY":["null"], "EducationF":["null"], "EducationW":["null"], "EducationFY":["null"], "ScienceF":["null"], "ScienceW":["null"], "ScienceFY":["null"]}